Fast_Hist/FH.py
Fast_Hist/__init__.py
Fast_Hist-0.0.1.dist-info/LICENSE
Fast_Hist-0.0.1.dist-info/METADATA
Fast_Hist-0.0.1.dist-info/WHEEL
Fast_Hist-0.0.1.dist-info/top_level.txt
Fast_Hist-0.0.1.dist-info/RECORD
