Metadata-Version: 2.1
Name: Fast-Hist
Version: 0.0.1
Summary: fast way to plot a histogram
Home-page: UNKNOWN
Author: Batol Hamoud
Author-email: batoulmhamoud509@gmail.com
License: UNKNOWN
Platform: UNKNOWN
Classifier: Programming Language :: Python :: 3
Classifier: License :: OSI Approved :: MIT License
Classifier: Operating System :: OS Independent
Requires-Python: >=3.7
License-File: LICENSE
